setup.py
aiogithubauth/__init__.py
aiogithubauth.egg-info/PKG-INFO
aiogithubauth.egg-info/SOURCES.txt
aiogithubauth.egg-info/dependency_links.txt
aiogithubauth.egg-info/requires.txt
aiogithubauth.egg-info/top_level.txt