Metadata-Version: 1.1
Name: aiogithubauth
Version: 0.3.0
Summary: github auth middleware for aiohttp
Home-page: https://github.com/CanopyTax/aiohttp-github-auth
Author: nhumrich
Author-email: nick@humrich.us
License: Apache
Platform: UNKNOWN
Classifier: Development Status :: 4 - Beta
Classifier: Intended Audience :: Developers
Classifier: Natural Language :: English
Classifier: Programming Language :: Python
Classifier: Programming Language :: Python :: 3.5
